NCGR/dcnorm.py
NCGR/ncgr.py
NCGR/sitdates.py
NCGR-1.0.2.dist-info/LICENSE
NCGR-1.0.2.dist-info/METADATA
NCGR-1.0.2.dist-info/WHEEL
NCGR-1.0.2.dist-info/top_level.txt
NCGR-1.0.2.dist-info/RECORD
